YWP/__init__.py
YWP-15.2.dist-info/METADATA
YWP-15.2.dist-info/WHEEL
YWP-15.2.dist-info/entry_points.txt
YWP-15.2.dist-info/top_level.txt
YWP-15.2.dist-info/RECORD
