Metadata-Version: 2.1
Name: YWP
Version: 15.2
Summary: This is a library to simplify the Python language for beginners while adding some features that are not found in other libraries
Home-page: https://github.com/YourWantedProducts/YWP_Python
Author: Your Wanted Products (YWP)
Author-email: pbstzidr@ywp.freewebhostmost.com
Classifier: Programming Language :: Python :: 3
Requires-Python: >=3.6
Requires-Dist: SpeechRecognition ==3.10.4
Requires-Dist: dill ==0.3.8
Requires-Dist: flask-cors ==4.0.1
Requires-Dist: flask ==3.0.3
Requires-Dist: googletrans ==4.0.0rc1
Requires-Dist: gtts ==2.5.1
Requires-Dist: joblib ==1.4.2
Requires-Dist: moviepy ==1.0.3
Requires-Dist: nltk ==3.8.1
Requires-Dist: pyaudio ==0.2.14
Requires-Dist: pycryptodome ==3.20.0
Requires-Dist: pygame ==2.5.2
Requires-Dist: pyttsx3 ==2.90
Requires-Dist: requests ==2.31.0
Requires-Dist: selenium ==4.22.0
Requires-Dist: setuptools ==68.1.2
Requires-Dist: sounddevice ==0.4.7
Requires-Dist: tensorflow ==2.16.1
Requires-Dist: tflearn ==0.5.0
Requires-Dist: tqdm ==4.66.4
Requires-Dist: twine ==5.1.0
Requires-Dist: vosk ==0.3.45
Requires-Dist: wheel ==0.43.0
